Workbook

Sheet Summary
C2: Retail finance review
C3: Synthetic retailer | Actuals Jan 2025-Jun 2026 | Forecast Jul 2026-Jun 2027 | USD
C5: Metric | D5: Value
C6: Selected case | D6: =Assumptions!C12 -> Base
C7: Forecast revenue | D7: =SUM(Forecast!H5:H16) -> 13837306
C8: Forecast EBITDA | D8: =SUM(Forecast!L5:L16) -> 2224186.6
C9: Forecast free cash flow | D9: =SUM(Forecast!T5:T16) -> 1396729.5
C10: Ending cash | D10: =Forecast!V16 -> 2296729.5
C11: Actual EBITDA vs budget | D11: ='Variance bridge'!D11-'Variance bridge'!D5 -> -319865.13
C12: Seasonal holdout WAPE | D12: 0.02837189
C13: Trailing mean holdout WAPE | D13: 0.25317279
C14: Synthetic source records | D14: 3240
C21: Month | D21: Revenue | E21: EBITDA
C22: 2025-01 | D22: 857947.12 | E22: 88637.011
C23: 2025-02 | D23: 872546.5 | E23: 104709.64
C24: 2025-03 | D24: 995053.26 | E24: 140331.13
C25: 2025-04 | D25: 961530.33 | E25: 115550.95
C26: 2025-05 | D26: 983531.47 | E26: 147275.93
C27: 2025-06 | D27: 961942.23 | E27: 123663.94
C28: 2025-07 | D28: 964720.5 | E28: 122096.28
C29: 2025-08 | D29: 981775.61 | E29: 137516.09
C30: 2025-09 | D30: 951884.47 | E30: 129401.67
C31: 2025-10 | D31: 993976.22 | E31: 135555.29
C32: 2025-11 | D32: 1350354.3 | E32: 266447.86
C33: 2025-12 | D33: 1320946.2 | E33: 233733.32
... C39: 2026-06 | D39: 1014065.3 | E39: 149993.47

Sheet Assumptions
C2: Forecast assumptions
C3: Blue values are editable. Change D5: 1 Base, 2 Downside, 3 Upside.
C5: Selected case | D5: 1
C7: Case | D7: Demand change | E7: Price change | F7: Cost change | G7: Inventory days | H7: Payable days
C8: Base | D8: 0.06 | E8: 0.01 | F8: 0.02 | G8: 38 | H8: 30
C9: Downside | D9: -0.08 | E9: -0.02 | F9: 0.06 | G9: 52 | H9: 25
C10: Upside | D10: 0.13 | E10: 0.02 | F10: 0.01 | G10: 32 | H10: 35
C12: =CHOOSE($D$5,C8,C9,C10) -> Base | D12: =CHOOSE($D$5,D8,D9,D10) -> 0.06 | E12: =CHOOSE($D$5,E8,E9,E10) -> 0.01 | F12: =CHOOSE($D$5,F8,F9,F10) -> 0.02 | G12: =CHOOSE($D$5,G8,G9,G10) -> 38 | H12: =CHOOSE($D$5,H8,H9,H10) -> 30
C15: Other assumptions | D15: Value
C16: Fixed monthly expense | D16: 165240
C17: Depreciation | D17: 18000
C18: Monthly capex | D18: 25000
C19: Tax rate | D19: 0.25
C20: Receivable days | D20: 2
C21: Opening cash | D21: 900000
C22: Opening inventory days | D22: 38
C23: Opening payable days | D23: 30

Sheet Forecast
C2: Twelve month rolling forecast
C3: Same build for all cases. Actual history stays unchanged.
C4: Month | D4: Units | E4: Net price | F4: Variable / unit | G4: Merchandise share | H4: Revenue | I4: Variable costs | J4: Merchandise COGS | K4: Fixed costs | L4: EBITDA | M4: D&A | N4: Taxes | O4: Inventory | P4: Receivables | Q4: Payables | R4: Change NWC | S4: Capex | T4: Free cash flow | U4: Opening cash | V4: Ending cash
C5: 2026-07 | D5: =Actuals!D11*(SUM(Actuals!D17:D22)/SUM(Actuals!D5:D10))*(1+Assumptions!$D$12) -> 21717.589 | E5: =Actuals!$E$22/Actuals!$D$22*(1+Assumptions!$E$12) -> 49.337922 | F5: =Actuals!$F$22/Actuals!$D$22*(1+Assumptions!$F$12) -> 34.33732 | G5: =Actuals!$G$22/Actuals!$F$22 -> 0.88145092 | H5: =D5*E5 -> 1071500.7 | I5: =D5*F5 -> 745723.8 | J5: =I5*G5 -> 657318.94 | K5: =Assumptions!$D$16 -> 165240 | L5: =H5-I5-K5 -> 160536.9 | M5: =Assumptions!$D$17 -> 18000 | N5: =MAX(0,L5-M5)*Assumptions!$D$19 -> 35634.226 | O5: =J5*Assumptions!$G$12/31 -> 805745.79 | P5: =H5*Assumptions!$D$20/31 -> 69129.078 | Q5: =J5*Assumptions!$H$12/31 -> 636115.1 | R5: =O5+P5-Q5-(Actuals!G22*Assumptions!D22/30+Actuals!E22*Assumptions!D20/30-Actuals!G22*Assumptions!D23/30) -> 6892.5065 | S5: =Assumptions!$D$18 -> 25000 | T5: =L5-N5-R5-S5 -> 93010.171 | U5: =Assumptions!$D$21 -> 900000 | V5: =U5+T5 -> 993010.17
C6: 2026-08 | D6: =Actuals!D12*(SUM(Actuals!D17:D22)/SUM(Actuals!D5:D10))*(1+Assumptions!$D$12) -> 22028.51 | E6: =Actuals!$E$22/Actuals!$D$22*(1+Assumptions!$E$12) -> 49.337922 | F6: =Actuals!$F$22/Actuals!$D$22*(1+Assumptions!$F$12) -> 34.33732 | G6: =Actuals!$G$22/Actuals!$F$22 -> 0.88145092 | H6: =D6*E6 -> 1086840.9 | I6: =D6*F6 -> 756400.01 | J6: =I6*G6 -> 666729.49 | K6: =Assumptions!$D$16 -> 165240 | L6: =H6-I6-K6 -> 165200.91 | M6: =Assumptions!$D$17 -> 18000 | N6: =MAX(0,L6-M6)*Assumptions!$D$19 -> 36800.228 | O6: =J6*Assumptions!$G$12/31 -> 817281.31 | P6: =H6*Assumptions!$D$20/31 -> 70118.769 | Q6: =J6*Assumptions!$H$12/31 -> 645222.09 | R6: =O6+P6-Q6-(O5+P5-Q5) -> 3418.2215 | S6: =Assumptions!$D$18 -> 25000 | T6: =L6-N6-R6-S6 -> 99982.463 | U6: =V5 -> 993010.17 | V6: =U6+T6 -> 1092992.6
C7: 2026-09 | D7: =Actuals!D13*(SUM(Actuals!D17:D22)/SUM(Actuals!D5:D10))*(1+Assumptions!$D$12) -> 21245.207 | E7: =Actuals!$E$22/Actuals!$D$22*(1+Assumptions!$E$12) -> 49.337922 | F7: =Actuals!$F$22/Actuals!$D$22*(1+Assumptions!$F$12) -> 34.33732 | G7: =Actuals!$G$22/Actuals!$F$22 -> 0.88145092 | H7: =D7*E7 -> 1048194.3 | I7: =D7*F7 -> 729503.46 | J7: =I7*G7 -> 643021.5 | K7: =Assumptions!$D$16 -> 165240 | L7: =H7-I7-K7 -> 153450.88 | M7: =Assumptions!$D$17 -> 18000 | N7: =MAX(0,L7-M7)*Assumptions!$D$19 -> 33862.721 | O7: =J7*Assumptions!$G$12/30 -> 814493.9 | P7: =H7*Assumptions!$D$20/30 -> 69879.623 | Q7: =J7*Assumptions!$H$12/30 -> 643021.5 | R7: =O7+P7-Q7-(O6+P6-Q6) -> -825.97024 | S7: =Assumptions!$D$18 -> 25000 | T7: =L7-N7-R7-S7 -> 95414.133 | U7: =V6 -> 1092992.6 | V7: =U7+T7 -> 1188406.8
C8: 2026-10 | D8: =Actuals!D14*(SUM(Actuals!D17:D22)/SUM(Actuals!D5:D10))*(1+Assumptions!$D$12) -> 22448.527 | E8: =Actuals!$E$22/Actuals!$D$22*(1+Assumptions!$E$12) -> 49.337922 | F8: =Actuals!$F$22/Actuals!$D$22*(1+Assumptions!$F$12) -> 34.33732 | G8: =Actuals!$G$22/Actuals!$F$22 -> 0.88145092 | H8: =D8*E8 -> 1107563.7 | I8: =D8*F8 -> 770822.26 | J8: =I8*G8 -> 679441.99 | K8: =Assumptions!$D$16 -> 165240 | L8: =H8-I8-K8 -> 171501.41 | M8: =Assumptions!$D$17 -> 18000 | N8: =MAX(0,L8-M8)*Assumptions!$D$19 -> 38375.354 | O8: =J8*Assumptions!$G$12/31 -> 832864.38 | P8: =H8*Assumptions!$D$20/31 -> 71455.721 | Q8: =J8*Assumptions!$H$12/31 -> 657524.51 | R8: =O8+P8-Q8-(O7+P7-Q7) -> 5443.5677 | S8: =Assumptions!$D$18 -> 25000 | T8: =L8-N8-R8-S8 -> 102682.49 | U8: =V7 -> 1188406.8 | V8: =U8+T8 -> 1291089.3
C9: 2026-11 | D9: =Actuals!D15*(SUM(Actuals!D17:D22)/SUM(Actuals!D5:D10))*(1+Assumptions!$D$12) -> 30572.85 | E9: =Actuals!$E$22/Actuals!$D$22*(1+Assumptions!$E$12) -> 49.337922 | F9: =Actuals!$F$22/Actuals!$D$22*(1+Assumptions!$F$12) -> 34.33732 | G9: =Actuals!$G$22/Actuals!$F$22 -> 0.88145092 | H9: =D9*E9 -> 1508400.9 | I9: =D9*F9 -> 1049789.7 | J9: =I9*G9 -> 925338.12 | K9: =Assumptions!$D$16 -> 165240 | L9: =H9-I9-K9 -> 293371.14 | M9: =Assumptions!$D$17 -> 18000 | N9: =MAX(0,L9-M9)*Assumptions!$D$19 -> 68842.785 | O9: =J9*Assumptions!$G$12/30 -> 1172094.9 | P9: =H9*Assumptions!$D$20/30 -> 100560.06 | Q9: =J9*Assumptions!$H$12/30 -> 925338.12 | R9: =O9+P9-Q9-(O8+P8-Q8) -> 100521.3 | S9: =Assumptions!$D$18 -> 25000 | T9: =L9-N9-R9-S9 -> 99007.057 | U9: =V8 -> 1291089.3 | V9: =U9+T9 -> 1390096.3
C10: 2026-12 | D10: =Actuals!D16*(SUM(Actuals!D17:D22)/SUM(Actuals!D5:D10))*(1+Assumptions!$D$12) -> 29980.462 | E10: =Actuals!$E$22/Actuals!$D$22*(1+Assumptions!$E$12) -> 49.337922 | F10: =Actuals!$F$22/Actuals!$D$22*(1+Assumptions!$F$12) -> 34.33732 | G10: =Actuals!$G$22/Actuals!$F$22 -> 0.88145092 | H10: =D10*E10 -> 1479173.7 | I10: =D10*F10 -> 1029448.7 | J10: =I10*G10 -> 907408.53 | K10: =Assumptions!$D$16 -> 165240 | L10: =H10-I10-K10 -> 284484.98 | M10: =Assumptions!$D$17 -> 18000 | N10: =MAX(0,L10-M10)*Assumptions!$D$19 -> 66621.244 | O10: =J10*Assumptions!$G$12/31 -> 1112307.2 | P10: =H10*Assumptions!$D$20/31 -> 95430.562 | Q10: =J10*Assumptions!$H$12/31 -> 878137.29 | R10: =O10+P10-Q10-(O9+P9-Q9) -> -17716.382 | S10: =Assumptions!$D$18 -> 25000 | T10: =L10-N10-R10-S10 -> 210580.11 | U10: =V9 -> 1390096.3 | V10: =U10+T10 -> 1600676.4
C11: 2027-01 | D11: =Actuals!D17*(SUM(Actuals!D17:D22)/SUM(Actuals!D5:D10))*(1+Assumptions!$D$12) -> 20364.808 | E11: =Actuals!$E$22/Actuals!$D$22*(1+Assumptions!$E$12) -> 49.337922 | F11: =Actuals!$F$22/Actuals!$D$22*(1+Assumptions!$F$12) -> 34.33732 | G11: =Actuals!$G$22/Actuals!$F$22 -> 0.88145092 | H11: =D11*E11 -> 1004757.3 | I11: =D11*F11 -> 699272.93 | J11: =I11*G11 -> 616374.77 | K11: =Assumptions!$D$16 -> 165240 | L11: =H11-I11-K11 -> 140244.38 | M11: =Assumptions!$D$17 -> 18000 | N11: =MAX(0,L11-M11)*Assumptions!$D$19 -> 30561.094 | O11: =J11*Assumptions!$G$12/31 -> 755556.17 | P11: =H11*Assumptions!$D$20/31 -> 64823.052 | Q11: =J11*Assumptions!$H$12/31 -> 596491.71 | R11: =O11+P11-Q11-(O10+P10-Q10) -> -105713 | S11: =Assumptions!$D$18 -> 25000 | T11: =L11-N11-R11-S11 -> 190396.28 | U11: =V10 -> 1600676.4 | V11: =U11+T11 -> 1791072.7
C12: 2027-02 | D12: =Actuals!D18*(SUM(Actuals!D17:D22)/SUM(Actuals!D5:D10))*(1+Assumptions!$D$12) -> 20638.637 | E12: =Actuals!$E$22/Actuals!$D$22*(1+Assumptions!$E$12) -> 49.337922 | F12: =Actuals!$F$22/Actuals!$D$22*(1+Assumptions!$F$12) -> 34.33732 | G12: =Actuals!$G$22/Actuals!$F$22 -> 0.88145092 | H12: =D12*E12 -> 1018267.5 | I12: =D12*F12 -> 708675.49 | J12: =I12*G12 -> 624662.66 | K12: =Assumptions!$D$16 -> 165240 | L12: =H12-I12-K12 -> 144351.98 | M12: =Assumptions!$D$17 -> 18000 | N12: =MAX(0,L12-M12)*Assumptions!$D$19 -> 31587.994 | O12: =J12*Assumptions!$G$12/28 -> 847756.47 | P12: =H12*Assumptions!$D$20/28 -> 72733.39 | Q12: =J12*Assumptions!$H$12/28 -> 669281.42 | R12: =O12+P12-Q12-(O11+P11-Q11) -> 27320.928 | S12: =Assumptions!$D$18 -> 25000 | T12: =L12-N12-R12-S12 -> 60443.054 | U12: =V11 -> 1791072.7 | V12: =U12+T12 -> 1851515.8
C13: 2027-03 | D13: =Actuals!D19*(SUM(Actuals!D17:D22)/SUM(Actuals!D5:D10))*(1+Assumptions!$D$12) -> 22708.174 | E13: =Actuals!$E$22/Actuals!$D$22*(1+Assumptions!$E$12) -> 49.337922 | F13: =Actuals!$F$22/Actuals!$D$22*(1+Assumptions!$F$12) -> 34.33732 | G13: =Actuals!$G$22/Actuals!$F$22 -> 0.88145092 | H13: =D13*E13 -> 1120374.1 | I13: =D13*F13 -> 779737.83 | J13: =I13*G13 -> 687300.63 | K13: =Assumptions!$D$16 -> 165240 | L13: =H13-I13-K13 -> 175396.27 | M13: =Assumptions!$D$17 -> 18000 | N13: =MAX(0,L13-M13)*Assumptions!$D$19 -> 39349.068 | O13: =J13*Assumptions!$G$12/31 -> 842497.55 | P13: =H13*Assumptions!$D$20/31 -> 72282.2 | Q13: =J13*Assumptions!$H$12/31 -> 665129.64 | R13: =O13+P13-Q13-(O12+P12-Q12) -> -1558.332 | S13: =Assumptions!$D$18 -> 25000 | T13: =L13-N13-R13-S13 -> 112605.54 | U13: =V12 -> 1851515.8 | V13: =U13+T13 -> 1964121.3
C14: 2027-04 | D14: =Actuals!D20*(SUM(Actuals!D17:D22)/SUM(Actuals!D5:D10))*(1+Assumptions!$D$12) -> 23033.278 | E14: =Actuals!$E$22/Actuals!$D$22*(1+Assumptions!$E$12) -> 49.337922 | F14: =Actuals!$F$22/Actuals!$D$22*(1+Assumptions!$F$12) -> 34.33732 | G14: =Actuals!$G$22/Actuals!$F$22 -> 0.88145092 | H14: =D14*E14 -> 1136414 | I14: =D14*F14 -> 790901.02 | J14: =I14*G14 -> 697140.44 | K14: =Assumptions!$D$16 -> 165240 | L14: =H14-I14-K14 -> 180273.02 | M14: =Assumptions!$D$17 -> 18000 | N14: =MAX(0,L14-M14)*Assumptions!$D$19 -> 40568.256 | O14: =J14*Assumptions!$G$12/30 -> 883044.55 | P14: =H14*Assumptions!$D$20/30 -> 75760.936 | Q14: =J14*Assumptions!$H$12/30 -> 697140.44 | R14: =O14+P14-Q14-(O13+P13-Q13) -> 12014.949 | S14: =Assumptions!$D$18 -> 25000 | T14: =L14-N14-R14-S14 -> 102689.82 | U14: =V13 -> 1964121.3 | V14: =U14+T14 -> 2066811.1
C15: 2027-05 | D15: =Actuals!D21*(SUM(Actuals!D17:D22)/SUM(Actuals!D5:D10))*(1+Assumptions!$D$12) -> 23074.734 | E15: =Actuals!$E$22/Actuals!$D$22*(1+Assumptions!$E$12) -> 49.337922 | F15: =Actuals!$F$22/Actuals!$D$22*(1+Assumptions!$F$12) -> 34.33732 | G15: =Actuals!$G$22/Actuals!$F$22 -> 0.88145092 | H15: =D15*E15 -> 1138459.4 | I15: =D15*F15 -> 792324.52 | J15: =I15*G15 -> 698395.18 | K15: =Assumptions!$D$16 -> 165240 | L15: =H15-I15-K15 -> 180894.89 | M15: =Assumptions!$D$17 -> 18000 | N15: =MAX(0,L15-M15)*Assumptions!$D$19 -> 40723.723 | O15: =J15*Assumptions!$G$12/31 -> 856097.32 | P15: =H15*Assumptions!$D$20/31 -> 73448.994 | Q15: =J15*Assumptions!$H$12/31 -> 675866.3 | R15: =O15+P15-Q15-(O14+P14-Q14) -> -7985.0453 | S15: =Assumptions!$D$18 -> 25000 | T15: =L15-N15-R15-S15 -> 123156.21 | U15: =V14 -> 2066811.1 | V15: =U15+T15 -> 2189967.3
C16: 2027-06 | D16: =Actuals!D22*(SUM(Actuals!D17:D22)/SUM(Actuals!D5:D10))*(1+Assumptions!$D$12) -> 22647.08 | E16: =Actuals!$E$22/Actuals!$D$22*(1+Assumptions!$E$12) -> 49.337922 | F16: =Actuals!$F$22/Actuals!$D$22*(1+Assumptions!$F$12) -> 34.33732 | G16: =Actuals!$G$22/Actuals!$F$22 -> 0.88145092 | H16: =D16*E16 -> 1117359.9 | I16: =D16*F16 -> 777640.05 | J16: =I16*G16 -> 685451.54 | K16: =Assumptions!$D$16 -> 165240 | L16: =H16-I16-K16 -> 174479.83 | M16: =Assumptions!$D$17 -> 18000 | N16: =MAX(0,L16-M16)*Assumptions!$D$19 -> 39119.959 | O16: =J16*Assumptions!$G$12/30 -> 868238.62 | P16: =H16*Assumptions!$D$20/30 -> 74490.659 | Q16: =J16*Assumptions!$H$12/30 -> 685451.54 | R16: =O16+P16-Q16-(O15+P15-Q15) -> 3597.7281 | S16: =Assumptions!$D$18 -> 25000 | T16: =L16-N16-R16-S16 -> 106762.15 | U16: =V15 -> 2189967.3 | V16: =U16+T16 -> 2296729.5

Sheet Actuals
C2: Historical actuals
C3: SQL aggregates from data/orders.csv; source amounts preserved.
C4: Month | D4: Units | E4: Revenue | F4: Variable costs | G4: Merchandise COGS | H4: Fixed costs | I4: EBITDA
C5: 2025-01 | D5: 18302 | E5: 857947.12 | F5: 603260.1 | G5: 531265.68 | H5: 166050 | I5: 88637.011
C6: 2025-02 | D6: 18118 | E6: 872546.5 | F6: 600976.86 | G6: 529168.04 | H6: 166860 | I6: 104709.64
C7: 2025-03 | D7: 20290 | E7: 995053.26 | F7: 689482.13 | G7: 608270.28 | H7: 165240 | I7: 140331.13
C8: 2025-04 | D8: 20373 | E8: 961530.33 | F8: 679929.38 | G8: 598662.83 | H8: 166050 | I8: 115550.95
C9: 2025-05 | D9: 20555 | E9: 983531.47 | F9: 669395.54 | G9: 588995.3 | H9: 166860 | I9: 147275.93
C10: 2025-06 | D10: 20340 | E10: 961942.23 | F10: 673038.3 | G10: 592506.21 | H10: 165240 | I10: 123663.94
C11: 2025-07 | D11: 19907 | E11: 964720.5 | F11: 676574.22 | G11: 596886.15 | H11: 166050 | I11: 122096.28
C12: 2025-08 | D12: 20192 | E12: 981775.61 | F12: 677399.52 | G12: 597035.17 | H12: 166860 | I12: 137516.09
C13: 2025-09 | D13: 19474 | E13: 951884.47 | F13: 657242.79 | G13: 579715.15 | H13: 165240 | I13: 129401.67
C14: 2025-10 | D14: 20577 | E14: 993976.22 | F14: 692370.94 | G14: 610188.04 | H14: 166050 | I14: 135555.29
C15: 2025-11 | D15: 28024 | E15: 1350354.3 | F15: 917046.4 | G15: 807640.43 | H15: 166860 | I15: 266447.86
C16: 2025-12 | D16: 27481 | E16: 1320946.2 | F16: 921972.93 | G16: 811601.08 | H16: 165240 | I16: 233733.32
... C22: 2026-06 | D22: 20759 | E22: 1014065.3 | F22: 698831.79 | G22: 615985.93 | H22: 165240 | I22: 149993.47

Sheet Variance bridge
C2: EBITDA variance bridge
C3: Exact sequence: volume, mix, net price, variable cost and fixed cost. Positive increases profit.
C4: Driver | D4: USD
C5: Budget EBITDA | D5: =SUM(L15:L176)-SUM(J15:J176) -> 2947464.3
C6: Volume | D6: =(SUM(G15:G176)-SUM(D15:D176))*(SUM(L15:L176)/SUM(D15:D176)) -> 129786.44
C7: Mix | D7: =SUMPRODUCT(G15:G176,E15:E176)-SUMPRODUCT(G15:G176,F15:F176)-SUM(G15:G176)*SUM(L15:L176)/SUM(D15:D176) -> -16855.869
C8: Price | D8: =SUM(N15:N176) -> -109877
C9: Variable costs | D9: =SUM(O15:O176) -> -250018.7
C10: Fixed costs | D10: =SUM(J15:J176)-SUM(K15:K176) -> -72900
C11: Actual EBITDA | D11: =SUM(M15:M176)-SUM(K15:K176) -> 2627599.2
C12: Reconciliation difference | D12: =D11-D5-SUM(D6:D10) -> 0
C14: Segment key | D14: Budget units | E14: Budget price | F14: Budget unit cost | G14: Actual units | H14: Actual price | I14: Actual unit cost | J14: Budget fixed | K14: Actual fixed | L14: Budget contribution | M14: Actual contribution | N14: Price effect | O14: Cost effect
C15: 2025-01 East Electronics | D15: 1530 | E15: 95 | F15: 67.2 | G15: 1598 | H15: 91.8176 | I15: 67.091 | J15: 18000 | K15: 18450 | L15: =D15*(E15-F15) -> 42534 | M15: =G15*(H15-I15) -> 39513.107 | N15: =G15*(H15-E15) -> -5085.4752 | O15: =-G15*(I15-F15) -> 174.182
C16: 2025-01 East Home | D16: 1845 | E16: 44 | F16: 27.1 | G16: 1765 | H16: 44.4043 | I16: 27.9813 | J16: 18000 | K16: 18450 | L16: =D16*(E16-F16) -> 31180.5 | M16: =G16*(H16-I16) -> 28986.595 | N16: =G16*(H16-E16) -> 713.5895 | O16: =-G16*(I16-F16) -> -1555.4945
C17: 2025-01 East Essentials | D17: 2160 | E17: 19 | F17: 12.8 | G17: 2370 | H17: 18.4341 | I17: 12.9391 | J17: 18000 | K17: 18450 | L17: =D17*(E17-F17) -> 13392 | M17: =G17*(H17-I17) -> 13023.15 | N17: =G17*(H17-E17) -> -1341.183 | O17: =-G17*(I17-F17) -> -329.667
C18: 2025-01 Central Electronics | D18: 1665 | E18: 95 | F18: 67.2 | G18: 1526 | H18: 92.9212 | I18: 68.4066 | J18: 18000 | K18: 18450 | L18: =D18*(E18-F18) -> 46287 | M18: =G18*(H18-I18) -> 37409.28 | N18: =G18*(H18-E18) -> -3172.2488 | O18: =-G18*(I18-F18) -> -1841.2716
C19: 2025-01 Central Home | D19: 1980 | E19: 44 | F19: 27.1 | G19: 1813 | H19: 42.9849 | I19: 27.9195 | J19: 18000 | K19: 18450 | L19: =D19*(E19-F19) -> 33462 | M19: =G19*(H19-I19) -> 27313.57 | N19: =G19*(H19-E19) -> -1840.3763 | O19: =-G19*(I19-F19) -> -1485.7535
C20: 2025-01 Central Essentials | D20: 2295 | E20: 19 | F20: 12.8 | G20: 2351 | H20: 18.5863 | I20: 13.1211 | J20: 18000 | K20: 18450 | L20: =D20*(E20-F20) -> 14229 | M20: =G20*(H20-I20) -> 12848.685 | N20: =G20*(H20-E20) -> -972.6087 | O20: =-G20*(I20-F20) -> -754.9061
C21: 2025-01 West Electronics | D21: 1800 | E21: 95 | F21: 67.2 | G21: 1944 | H21: 91.712 | I21: 70.1228 | J21: 18000 | K21: 18450 | L21: =D21*(E21-F21) -> 50040 | M21: =G21*(H21-I21) -> 41969.405 | N21: =G21*(H21-E21) -> -6391.872 | O21: =-G21*(I21-F21) -> -5681.9232
C22: 2025-01 West Home | D22: 2115 | E22: 44 | F22: 27.1 | G22: 2235 | H22: 43.3583 | I22: 26.7806 | J22: 18000 | K22: 18450 | L22: =D22*(E22-F22) -> 35743.5 | M22: =G22*(H22-I22) -> 37051.16 | N22: =G22*(H22-E22) -> -1434.1995 | O22: =-G22*(I22-F22) -> 713.859
C23: 2025-01 West Essentials | D23: 2430 | E23: 19 | F23: 12.8 | G23: 2700 | H23: 18.7187 | I23: 12.5809 | J23: 18000 | K23: 18450 | L23: =D23*(E23-F23) -> 15066 | M23: =G23*(H23-I23) -> 16572.06 | N23: =G23*(H23-E23) -> -759.51 | O23: =-G23*(I23-F23) -> 591.57
C24: 2025-02 East Electronics | D24: 1530 | E24: 95 | F24: 67.2 | G24: 1423 | H24: 96.5057 | I24: 68.9685 | J24: 18000 | K24: 18540 | L24: =D24*(E24-F24) -> 42534 | M24: =G24*(H24-I24) -> 39185.436 | N24: =G24*(H24-E24) -> 2142.6111 | O24: =-G24*(I24-F24) -> -2516.5755
C25: 2025-02 East Home | D25: 1845 | E25: 44 | F25: 27.1 | G25: 1992 | H25: 44.3865 | I25: 27.6577 | J25: 18000 | K25: 18540 | L25: =D25*(E25-F25) -> 31180.5 | M25: =G25*(H25-I25) -> 33323.77 | N25: =G25*(H25-E25) -> 769.908 | O25: =-G25*(I25-F25) -> -1110.9384
C26: 2025-02 East Essentials | D26: 2160 | E26: 19 | F26: 12.8 | G26: 2407 | H26: 18.7665 | I26: 13.0806 | J26: 18000 | K26: 18540 | L26: =D26*(E26-F26) -> 13392 | M26: =G26*(H26-I26) -> 13685.961 | N26: =G26*(H26-E26) -> -562.0345 | O26: =-G26*(I26-F26) -> -675.4042
... C176: 2026-06 West Essentials | D176: 2808 | E176: 19.19 | F176: 12.8 | G176: 3000 | H176: 19.501 | I176: 13.5173 | J176: 18000 | K176: 18360 | L176: =D176*(E176-F176) -> 17943.12 | M176: =G176*(H176-I176) -> 17951.1 | N176: =G176*(H176-E176) -> 933 | O176: =-G176*(I176-F176) -> -2151.9

Sheet Segments
C2: Segment actuals
C3: Nine category-region combinations per month. Native PivotTable added in Excel.
C4: Month | D4: Region | E4: Category | F4: Units | G4: Revenue | H4: Variable costs | I4: Merchandise COGS | J4: Fixed costs | K4: EBITDA
C5: 2025-01 | D5: Central | E5: Electronics | F5: 1526 | G5: 141797.75 | H5: 104388.47 | I5: 96310.743 | J5: 18450 | K5: 18959.28
C6: 2025-01 | D6: Central | E6: Essentials | F6: 2351 | G6: 43696.391 | H6: 30847.706 | I6: 24099.866 | J6: 18450 | K6: -5601.3148
C7: 2025-01 | D7: Central | E7: Home | F7: 1813 | G7: 77931.624 | H7: 50618.054 | I7: 42959.942 | J7: 18450 | K7: 8863.5702
C8: 2025-01 | D8: East | E8: Electronics | F8: 1598 | G8: 146724.52 | H8: 107211.42 | I8: 98915.241 | J8: 18450 | K8: 21063.107
C9: 2025-01 | D9: East | E9: Essentials | F9: 2370 | G9: 43688.817 | H9: 30665.667 | I9: 23957.382 | J9: 18450 | K9: -5426.85
C10: 2025-01 | D10: East | E10: Home | F10: 1765 | G10: 78373.59 | H10: 49386.995 | I10: 41915.043 | J10: 18450 | K10: 10536.595
C11: 2025-01 | D11: West | E11: Electronics | F11: 1944 | G11: 178288.13 | H11: 136318.72 | I11: 125770.38 | J11: 18450 | K11: 23519.405
C12: 2025-01 | D12: West | E12: Essentials | F12: 2700 | G12: 50540.49 | H12: 33968.43 | I12: 26537.76 | J12: 18450 | K12: -1877.94
C13: 2025-01 | D13: West | E13: Home | F13: 2235 | G13: 96905.801 | H13: 59854.641 | I13: 50799.315 | J13: 18450 | K13: 18601.16
C14: 2025-02 | D14: Central | E14: Electronics | F14: 1805 | G14: 171837.08 | H14: 127147.99 | I14: 117309.12 | J14: 18540 | K14: 26149.093
C15: 2025-02 | D15: Central | E15: Essentials | F15: 2198 | G15: 41025.45 | H15: 27621.826 | I15: 21579.524 | J15: 18540 | K15: -5136.3762
C16: 2025-02 | D16: Central | E16: Home | F16: 2042 | G16: 90501.644 | H16: 54170.38 | I16: 45974.813 | J16: 18540 | K16: 17791.264
... C166: 2026-06 | D166: West | E166: Home | F166: 2419 | G166: 103775.83 | H166: 65876.143 | I166: 55909.621 | J166: 18360 | K166: 19539.683

Sheet Checks
C2: Model reconciliations
C3: Independent diagnostics. No planning formulas depend on this sheet.
C4: Check | D4: Difference
C5: Variance bridge | D5: ='Variance bridge'!D12 -> 0
C6: Cash flow identity | D6: =SUM(Forecast!T5:T16)-(SUM(Forecast!L5:L16)-SUM(Forecast!N5:N16)-SUM(Forecast!R5:R16)-SUM(Forecast!S5:S16)) -> 0
C7: Cash continuity | D7: =Forecast!V16-Assumptions!D21-SUM(Forecast!T5:T16) -> 0
C8: Source revenue tie | D8: =SUM(Actuals!E5:E22)-SUM(Segments!G5:G166) -> 0

Sheet Pivot review
C2: Native Excel PivotTable
C3: Region | D3: (All)
D5: Column Labels
D6: Electronics | F6: Essentials | H6: Home | J6: Total Revenue USD | K6: Total EBITDA USD
C7: Row Labels | D7: Revenue USD | E7: EBITDA USD | F7: Revenue USD | G7: EBITDA USD | H7: Revenue USD | I7: EBITDA USD
C8: 2025-01 | D8: 466810.4 | E8: 63541.791 | F8: 137925.7 | G8: -12906.105 | H8: 253211.01 | I8: 38001.325 | J8: 857947.12 | K8: 88637.011
C9: 2025-02 | D9: 468389.4 | E9: 71651.174 | F9: 129402.54 | G9: -16615.2 | H9: 274754.55 | I9: 49673.67 | J9: 872546.5 | K9: 104709.64
C10: 2025-03 | D10: 561719.04 | E10: 100519.65 | F10: 145452.79 | G10: -12143.204 | H10: 287881.44 | I10: 51954.691 | J10: 995053.26 | K10: 140331.13
C11: 2025-04 | D11: 520488.12 | E11: 76359.964 | F11: 151121.65 | G11: -9977.8849 | H11: 289920.56 | I11: 49168.871 | J11: 961530.33 | K11: 115550.95
C12: 2025-05 | D12: 527049.14 | E12: 93688.384 | F12: 156235.99 | G12: -3822.6247 | H12: 300246.34 | I12: 57410.168 | J12: 983531.47 | K12: 147275.93
C13: 2025-06 | D13: 518152.74 | E13: 80053.174 | F13: 147839.55 | G13: -11251.342 | H13: 295949.95 | I13: 54862.104 | J13: 961942.23 | K13: 123663.94
C14: 2025-07 | D14: 540580.07 | E14: 85898.994 | F14: 145224.02 | G14: -11571.191 | H14: 278916.41 | I14: 47768.474 | J14: 964720.5 | K14: 122096.28
C15: 2025-08 | D15: 533544.32 | E15: 84871.842 | F15: 149987.92 | G15: -8365.0923 | H15: 298243.37 | I15: 61009.341 | J15: 981775.61 | K15: 137516.09
C16: 2025-09 | D16: 524927.94 | E16: 84034.8 | F16: 144362.44 | G16: -8679.5905 | H16: 282594.09 | I16: 54046.465 | J16: 951884.47 | K16: 129401.67
C17: 2025-10 | D17: 541337.68 | E17: 87719.885 | F17: 148999.12 | G17: -8178.2955 | H17: 303639.43 | I17: 56013.697 | J17: 993976.22 | K17: 135555.29
C18: 2025-11 | D18: 731306.18 | E18: 154189.6 | F18: 204038.75 | G18: 11900.03 | H18: 415009.32 | I18: 100358.23 | J18: 1350354.3 | K18: 266447.86
C19: 2025-12 | D19: 706506.08 | E19: 128825.77 | F19: 201297.14 | G19: 5233.1829 | H19: 413143.02 | I19: 99674.361 | J19: 1320946.2 | K19: 233733.32
... C26: Grand Total | D26: 9876870.3 | E26: 1698161 | F26: 2756848.2 | G26: -132616.47 | H26: 5496023.1 | I26: 1062054.7 | J26: 18129742 | K26: 2627599.2
